README.rst
setup.py
statwalker/__init__.py
statwalker/getsid.py
statwalker/statwalker.py
statwalker.egg-info/PKG-INFO
statwalker.egg-info/SOURCES.txt
statwalker.egg-info/dependency_links.txt
statwalker.egg-info/entry_points.txt
statwalker.egg-info/top_level.txt