Metadata-Version: 1.1
Name: statwalker
Version: 1.1
Summary: Walk file systems and collect stats
Home-page: https://github.com/sganis/statwalker
Author: sganis
Author-email: sganis@gmail.com
License: MIT
Keywords: statwalker walk filesytem stats recursively
Platform: UNKNOWN
Classifier: Development Status :: 5 - Production/Stable
Classifier: License :: OSI Approved :: MIT License
Classifier: Programming Language :: Python :: 2.7
